magictk/__init__.py
magictk/_window_ctl.py
magictk/_window_size.py
magictk/basicwindow.py
magictk/button.py
magictk/checkbox.py
magictk/color_tmpl.py
magictk/entry.py
magictk/fontconfig.py
magictk/frame.py
magictk/icon.ico
magictk/icon.py
magictk/mtk.py
magictk/photoload.py
magictk/progressbar.py
magictk/res.pickle
magictk/scrollbar.py
magictk/select.py
magictk/style.py
magictk/submenu.py
magictk/window.py
magictk/workspace.py
magictk-1.0.1.62.dist-info/LICENSE
magictk-1.0.1.62.dist-info/METADATA
magictk-1.0.1.62.dist-info/WHEEL
magictk-1.0.1.62.dist-info/top_level.txt
magictk-1.0.1.62.dist-info/RECORD
